<?xml version="1.0" encoding="UTF-8" standalone="yes"?>
<root>
    <visualValidationSettings>
        <enabled>true</enabled>
        <ocrConfiguration>
            <enabled>true</enabled>
            <engine>tesseract</engine>
        </ocrConfiguration>
        <matcherConfiguration>
            <locationMatchMargin>0</locationMatchMargin>
            <loggingEnabled>true</loggingEnabled>
            <failedToMatchPercentageThreshold>75</failedToMatchPercentageThreshold>
        </matcherConfiguration>
        <protocol>desktop_generic/Protocol_desktop_generic</protocol>
    </visualValidationSettings>
    <tesseractSettings>
        <dataPath>C:\Users\Tycho\AppData\Local\Tesseract-OCR\tessdata</dataPath>
        <language>eng</language>
        <imageResolution>144</imageResolution>
        <loggingEnabled>false</loggingEnabled>
        <saveImageBufferToDisk>true</saveImageBufferToDisk>
    </tesseractSettings>
    <widgetTextConfiguration>
        <widget>
            <role>UIAGroup</role>
            <tag></tag>
            <ignore>true</ignore>
            <ancestor></ancestor>
        </widget>
        <widget>
            <role>UIASlider</role>
            <tag></tag>
            <ignore>true</ignore>
            <ancestor></ancestor>
        </widget>
        <widget>
            <role>UIAMenuBar</role>
            <tag></tag>
            <ignore>true</ignore>
            <ancestor></ancestor>
        </widget>
        <widget>
            <role>UIAPane</role>
            <tag></tag>
            <ignore>true</ignore>
            <ancestor></ancestor>
        </widget>
        <widget>
            <role>UIAHeader</role>
            <tag></tag>
            <ignore>true</ignore>
            <ancestor></ancestor>
        </widget>
        <widget>
            <role>UIATree</role>
            <tag></tag>
            <ignore>true</ignore>
            <ancestor></ancestor>
        </widget>
        <widget>
            <role>UIAButton</role>
            <tag></tag>
            <ignore>true</ignore>
            <ancestor>::UIATitleBar::UIAWindow::Process</ancestor>
        </widget>
        <widget>
            <role>UIAButton</role>
            <tag></tag>
            <ignore>true</ignore>
            <ancestor>::UIAGroup::UIAGroup::UIAGroup::UIAGroup::UIAPane::UIAWindow::Process</ancestor>
        </widget>
        <widget>
            <role>UIAButton</role>
            <tag></tag>
            <ignore>true</ignore>
            <ancestor>::UIAGroup::UIAGroup::UIAGroup::UIAPane::UIAWindow::Process</ancestor>
        </widget>
        <widget>
            <role>UIAButton</role>
            <tag></tag>
            <ignore>true</ignore>
            <ancestor>::UIAToolBar::UIAPane::UIAPane::UIAPane::UIAWindow::Process</ancestor>
        </widget>
        <widget>
            <role>UIAToolBar</role>
            <tag></tag>
            <ignore>true</ignore>
            <ancestor></ancestor>
        </widget>
        <widget>
            <role>UIAEdit</role>
            <tag>UIAValueValue</tag>
            <ignore>false</ignore>
            <ancestor></ancestor>
        </widget>
        <widget>
            <role>UIAMenuItem</role>
            <tag></tag>
            <ignore>true</ignore>
            <ancestor>::UIAMenuBar::UIATitleBar::UIAWindow::Process</ancestor>
        </widget>
        <widget>
            <role>UIAEdit</role>
            <tag></tag>
            <ignore>true</ignore>
            <ancestor>::UIAGroup::UIAGroup::UIAPane::UIAWindow::Process</ancestor>
        </widget>
        <widget>
            <role>UIAList</role>
            <tag></tag>
            <ignore>true</ignore>
            <ancestor></ancestor>
        </widget>
        <widget>
            <role>UIAScrollBar</role>
            <tag></tag>
            <ignore>true</ignore>
            <ancestor></ancestor>
        </widget>
        <widget>
            <role>UIAThumb</role>
            <tag></tag>
            <ignore>true</ignore>
            <ancestor></ancestor>
        </widget>
        <widget>
            <role>UIAButton</role>
            <tag></tag>
            <ignore>true</ignore>
            <ancestor>::UIAScrollBar::UIAList::UIAPane::UIAPane::UIAPane::UIAWindow::Process</ancestor>
        </widget>
        <widget>
            <role>UIAButton</role>
            <tag></tag>
            <ignore>true</ignore>
            <ancestor>::UIAToolBar::UIAPane::UIAPane::UIAPane::UIAPane::UIAWindow::Process</ancestor>
        </widget>
        <widget>
            <role>UIAButton</role>
            <tag></tag>
            <ignore>true</ignore>
            <ancestor>::UIAGroup::UIAGroup::UIAPane::UIAPane::UIAPane::UIAPane::UIAWindow::Process</ancestor>
        </widget>
        <widget>
            <role>UIAMenu</role>
            <tag></tag>
            <ignore>true</ignore>
            <ancestor></ancestor>
        </widget>
        <widget>
            <role>UIAButton</role>
            <tag></tag>
            <ignore>true</ignore>
            <ancestor>::UIATitleBar::UIAWindow::UIAWindow::Process</ancestor>
        </widget>
        <widget>
            <role>UIAImage</role>
            <tag></tag>
            <ignore>true</ignore>
            <ancestor></ancestor>
        </widget>
        <widget>
            <role>UIAProgressBar</role>
            <tag></tag>
            <ignore>true</ignore>
            <ancestor></ancestor>
        </widget>
        <loggingEnabled>true</loggingEnabled>
    </widgetTextConfiguration>
    <version>1</version>
</root>
